MANIFEST.in
README.md
requirements.txt
setup.cfg
setup.py
ansible_bundle/__init__.py
ansible_bundle/bundle.py
ansible_bundle/defaults.py
ansible_bundle/main.py
ansible_bundle/scm.py
ansible_bundle/shell.py
ansible_bundle/worker.py
ansible_bundle.egg-info/PKG-INFO
ansible_bundle.egg-info/SOURCES.txt
ansible_bundle.egg-info/dependency_links.txt
ansible_bundle.egg-info/entry_points.txt
ansible_bundle.egg-info/not-zip-safe
ansible_bundle.egg-info/requires.txt
ansible_bundle.egg-info/top_level.txt
test/test_ansible_bundle.py