Metadata-Version: 1.1
Name: ansible-bundle
Version: 0.6.0
Summary: Manage ansible role and modules versioned dependencies.
Home-page: https://github.com/devopsysadmin/ansible-bundle
Author: David PG
Author-email: david.3pwood@gmail.com
License: GPL v2
Keywords: ansible roles modules
Platform: UNKNOWN
Classifier: Development Status :: 4 - Beta
Classifier: Environment :: Console
Classifier: Intended Audience :: Developers
Classifier: License :: OSI Approved :: GNU General Public License v2 (GPLv2)
Classifier: Operating System :: POSIX
Classifier: Programming Language :: Python :: 2
Classifier: Topic :: Utilities
